dgmetrics/__init__.py
dgmetrics/config.py
dgmetrics/logger.py
dgmetrics/metrics.py
dgmetrics/watchers/redis.py
dgmetrics-1.0.0a11.dist-info/licenses/LICENSE
dgmetrics-1.0.0a11.dist-info/METADATA
dgmetrics-1.0.0a11.dist-info/WHEEL
dgmetrics-1.0.0a11.dist-info/top_level.txt
dgmetrics-1.0.0a11.dist-info/RECORD
