Metadata-Version: 2.4
Name: dgmetrics
Version: 1.0.0a11
Summary: Prometheus metrics client
Author-email: "r.rasputin" <r.rasputin@s7.ru>
License: MIT License
Project-URL: Homepage, https://gitlab.com/gng-group/dgmetric
Project-URL: BugTracker, https://gitlab.com/gng-group/dgmetric/issues
Keywords: prometheus-client,metrics
Classifier: Development Status :: 4 - Beta
Classifier: Intended Audience :: Developers
Classifier: License :: OSI Approved :: MIT License
Classifier: Programming Language :: Python :: 3.10
Classifier: Programming Language :: Python :: 3.11
Classifier: Programming Language :: Python :: 3.12
Classifier: Programming Language :: Python :: 3.13
Classifier: Operating System :: OS Independent
Classifier: Topic :: Software Development :: Libraries :: Python Modules
Classifier: Topic :: System :: Distributed Computing
Requires-Python: >=3.10
License-File: LICENSE
Requires-Dist: pydantic<3.0.0,>=2.11.3
Requires-Dist: prometheus-client<0.22.0,>=0.21.1
Provides-Extra: redis
Requires-Dist: dgredis<0.2.0,>=0.1.2; extra == "redis"
Requires-Dist: apscheduler<4.0.0,>=3.11.1; extra == "redis"
Provides-Extra: all
Requires-Dist: dgredis<0.2.0,>=0.1.2; extra == "all"
Requires-Dist: apscheduler<4.0.0,>=3.11.1; extra == "all"
Dynamic: license-file
